bms_complete_regenerated/rtl/mcu/bms_current_limit_supervisor.v
module bms_current_limit_supervisor #(
    parameter [15:0] MCU_MAX_PACK_CURRENT  = 16'd300,
    parameter [15:0] MCU_WARN_PACK_CURRENT = 16'd240,
    parameter [11:0] MCU_MAX_TEMP          = 12'd80,
    parameter [11:0] MCU_WARN_TEMP         = 12'd65,
    parameter [3:0]  MCU_MAX_LMU_COUNT     = 4'd3
)(
    input  wire        clk,
    input  wire        rst_n,
    input  wire [15:0] pack_current,
    input  wire [11:0] max_temp_seen,
    input  wire [3:0]  active_lmu_count,
    input  wire        global_fault_in,
    output reg         current_warn,
    output reg         current_trip,
    output reg         thermal_warn,
    output reg         thermal_trip,
    output reg         lmu_count_fault,
    output reg [15:0]  allowed_current,
    output reg [7:0]   supervisor_code
);
    always @(posedge clk or negedge rst_n) begin
        if (!rst_n) begin
            current_warn    <= 1'b0;
            current_trip    <= 1'b0;
            thermal_warn    <= 1'b0;
            thermal_trip    <= 1'b0;
            lmu_count_fault <= 1'b0;
            allowed_current <= MCU_MAX_PACK_CURRENT;
            supervisor_code <= 8'h00;
        end else begin
            current_warn    <= (pack_current >= MCU_WARN_PACK_CURRENT);
            current_trip    <= (pack_current >= MCU_MAX_PACK_CURRENT);
            thermal_warn    <= (max_temp_seen >= MCU_WARN_TEMP);
            thermal_trip    <= (max_temp_seen >= MCU_MAX_TEMP);
            lmu_count_fault <= (active_lmu_count > MCU_MAX_LMU_COUNT);
            if (max_temp_seen >= MCU_MAX_TEMP)
                allowed_current <= MCU_MAX_PACK_CURRENT >> 2;
            else if (max_temp_seen >= MCU_WARN_TEMP)
                allowed_current <= MCU_MAX_PACK_CURRENT >> 1;
            else
                allowed_current <= MCU_MAX_PACK_CURRENT;
            if (global_fault_in)
                supervisor_code <= 8'hE1;
            else if (active_lmu_count > MCU_MAX_LMU_COUNT)
                supervisor_code <= 8'hE2;
            else if (pack_current >= MCU_MAX_PACK_CURRENT)
                supervisor_code <= 8'hE3;
            else if (max_temp_seen >= MCU_MAX_TEMP)
                supervisor_code <= 8'hE4;
            else if ((pack_current >= MCU_WARN_PACK_CURRENT) || (max_temp_seen >= MCU_WARN_TEMP))
                supervisor_code <= 8'hA1;
            else
                supervisor_code <= 8'h00;
        end
    end
endmodule

bms_complete/rtl/mcu/bms_spi_master.v
module bms_spi_master #(
    parameter [7:0] CLK_DIV = 8'd8,
    parameter [1:0] CPOL    = 2'd0,
    parameter [1:0] CPHA    = 2'd0
)(
    input  wire       clk,
    input  wire       rst_n,
    input  wire       start,
    input  wire [1:0] slave_sel,
    input  wire [7:0] tx_byte,
    input  wire       miso,
    output reg        busy,
    output reg        done,
    output reg  [7:0] rx_byte,
    output reg        sclk,
    output reg        mosi,
    output reg  [2:0] cs_n
);
    reg [7:0] clk_cnt;
    reg [3:0] bit_cnt;
    reg [7:0] tx_shift;
    reg [7:0] rx_shift;
    reg [1:0] state;

    localparam ST_IDLE  = 2'd0;
    localparam ST_SHIFT = 2'd1;
    localparam ST_DONE  = 2'd2;

    always @(posedge clk or negedge rst_n) begin
        if (!rst_n) begin
            clk_cnt  <= 8'd0;
            bit_cnt  <= 4'd0;
            tx_shift <= 8'd0;
            rx_shift <= 8'd0;
            state    <= ST_IDLE;
            busy     <= 1'b0;
            done     <= 1'b0;
            rx_byte  <= 8'd0;
            sclk     <= 1'b0;
            mosi     <= 1'b0;
            cs_n     <= 3'b111;
        end else begin
            case (state)
                ST_IDLE: begin
                    clk_cnt <= 8'd0;
                    bit_cnt <= 4'd0;
                    done    <= 1'b0;
                    busy    <= 1'b0;
                    sclk    <= CPOL[0];
                    cs_n    <= 3'b111;
                    if (start) begin
                        busy     <= 1'b1;
                        tx_shift <= tx_byte;
                        rx_shift <= 8'd0;
                        mosi     <= tx_byte[7];
                        case (slave_sel)
                            2'd0: cs_n <= 3'b110;
                            2'd1: cs_n <= 3'b101;
                            2'd2: cs_n <= 3'b011;
                            default: cs_n <= 3'b111;
                        endcase
                        state <= ST_SHIFT;
                    end
                end
                ST_SHIFT: begin
                    if (clk_cnt == (CLK_DIV - 1'b1)) begin
                        clk_cnt <= 8'd0;
                        sclk    <= ~sclk;
                        if (sclk == CPOL[0]) begin
                            rx_shift <= {rx_shift[6:0], miso};
                            if (bit_cnt == 4'd7) begin
                                rx_byte <= {rx_shift[6:0], miso};
                                state   <= ST_DONE;
                            end else begin
                                bit_cnt  <= bit_cnt + 4'd1;
                                tx_shift <= {tx_shift[6:0], 1'b0};
                                mosi     <= tx_shift[6];
                            end
                        end
                    end else begin
                        clk_cnt <= clk_cnt + 8'd1;
                    end
                end
                default: begin
                    cs_n <= 3'b111;
                    sclk <= CPOL[0];
                    busy <= 1'b0;
                    done <= 1'b1;
                    state <= ST_IDLE;
                end
            endcase
        end
    end
endmodule

bms_complete/rtl/mcu/bms_master_control_unit_enhanced.v
module bms_master_control_unit_enhanced(
    input  wire        clk,
    input  wire        rst_n,
    input  wire        start_poll,
    input  wire        spi_miso,
    input  wire [15:0] pack_current,
    input  wire [11:0] lmu0_temp_die,
    input  wire [11:0] lmu1_temp_die,
    input  wire [11:0] lmu2_temp_die,
    input  wire [15:0] lmu0_soc,
    input  wire [15:0] lmu1_soc,
    input  wire [15:0] lmu2_soc,
    input  wire [15:0] lmu0_soh,
    input  wire [15:0] lmu1_soh,
    input  wire [15:0] lmu2_soh,
    input  wire        lmu0_fault,
    input  wire        lmu1_fault,
    input  wire        lmu2_fault,
    input  wire [7:0]  lmu0_fault_code,
    input  wire [7:0]  lmu1_fault_code,
    input  wire [7:0]  lmu2_fault_code,
    output wire        spi_sclk,
    output wire        spi_mosi,
    output wire [2:0]  spi_cs_n,
    output reg  [15:0] pack_soc_avg,
    output reg  [15:0] pack_soh_avg,
    output reg         global_fault,
    output reg  [7:0]  global_fault_code,
    output reg  [1:0]  active_lmu_id,
    output reg         poll_busy,
    output wire        current_warn,
    output wire        current_trip,
    output wire        thermal_warn,
    output wire        thermal_trip,
    output wire        lmu_count_fault,
    output wire [15:0] allowed_current,
    output wire [7:0]  supervisor_code,
    output reg  [11:0] max_temp_seen
);
    reg        spi_start;
    reg [1:0]  spi_slave_sel;
    reg [7:0]  spi_tx_byte;
    wire       spi_busy;
    wire       spi_done;
    wire [7:0] spi_rx_byte;
    reg [2:0]  state;
    wire [3:0] active_lmu_count;

    assign active_lmu_count = 4'd3;

    localparam ST_IDLE  = 3'd0;
    localparam ST_LMU0  = 3'd1;
    localparam ST_LMU1  = 3'd2;
    localparam ST_LMU2  = 3'd3;
    localparam ST_EVAL  = 3'd4;

    bms_spi_master u_spi_master (
        .clk(clk), .rst_n(rst_n), .start(spi_start), .slave_sel(spi_slave_sel), .tx_byte(spi_tx_byte), .miso(spi_miso),
        .busy(spi_busy), .done(spi_done), .rx_byte(spi_rx_byte), .sclk(spi_sclk), .mosi(spi_mosi), .cs_n(spi_cs_n)
    );

    bms_current_limit_supervisor u_curr_sup (
        .clk(clk), .rst_n(rst_n), .pack_current(pack_current), .max_temp_seen(max_temp_seen), .active_lmu_count(active_lmu_count),
        .global_fault_in(global_fault), .current_warn(current_warn), .current_trip(current_trip), .thermal_warn(thermal_warn),
        .thermal_trip(thermal_trip), .lmu_count_fault(lmu_count_fault), .allowed_current(allowed_current), .supervisor_code(supervisor_code)
    );

    always @(posedge clk or negedge rst_n) begin
        if (!rst_n) begin
            spi_start         <= 1'b0;
            spi_slave_sel     <= 2'd0;
            spi_tx_byte       <= 8'h00;
            pack_soc_avg      <= 16'd0;
            pack_soh_avg      <= 16'd0;
            global_fault      <= 1'b0;
            global_fault_code <= 8'd0;
            active_lmu_id     <= 2'd0;
            poll_busy         <= 1'b0;
            max_temp_seen     <= 12'd0;
            state             <= ST_IDLE;
        end else begin
            spi_start <= 1'b0;
            case (state)
                ST_IDLE: begin
                    poll_busy <= 1'b0;
                    if (start_poll) begin
                        poll_busy     <= 1'b1;
                        active_lmu_id <= 2'd0;
                        spi_slave_sel <= 2'd0;
                        spi_tx_byte   <= 8'hB0;
                        spi_start     <= 1'b1;
                        state         <= ST_LMU0;
                    end
                end
                ST_LMU0: begin
                    if (spi_done) begin
                        active_lmu_id <= 2'd1;
                        spi_slave_sel <= 2'd1;
                        spi_tx_byte   <= 8'hB1;
                        spi_start     <= 1'b1;
                        state         <= ST_LMU1;
                    end
                end
                ST_LMU1: begin
                    if (spi_done) begin
                        active_lmu_id <= 2'd2;
                        spi_slave_sel <= 2'd2;
                        spi_tx_byte   <= 8'hB2;
                        spi_start     <= 1'b1;
                        state         <= ST_LMU2;
                    end
                end
                ST_LMU2: begin
                    if (spi_done)
                        state <= ST_EVAL;
                end
                default: begin
                    pack_soc_avg <= (lmu0_soc + lmu1_soc + lmu2_soc) / 3'd3;
                    pack_soh_avg <= (lmu0_soh + lmu1_soh + lmu2_soh) / 3'd3;
                    if ((lmu0_temp_die >= lmu1_temp_die) && (lmu0_temp_die >= lmu2_temp_die))
                        max_temp_seen <= lmu0_temp_die;
                    else if (lmu1_temp_die >= lmu2_temp_die)
                        max_temp_seen <= lmu1_temp_die;
                    else
                        max_temp_seen <= lmu2_temp_die;

                    global_fault <= lmu0_fault | lmu1_fault | lmu2_fault;
                    if (lmu0_fault)
                        global_fault_code <= lmu0_fault_code;
                    else if (lmu1_fault)
                        global_fault_code <= lmu1_fault_code;
                    else if (lmu2_fault)
                        global_fault_code <= lmu2_fault_code;
                    else
                        global_fault_code <= 8'h00;
                    poll_busy <= 1'b0;
                    state <= ST_IDLE;
                end
            endcase
        end
    end
endmodule

bms_complete_regenerated/tb/mcu/tb_bms_master_control_unit_enhanced.v
`timescale 1ns/1ns
module tb_bms_master_control_unit_enhanced;
    reg clk;
    reg rst_n;
    reg start_poll;
    reg spi_miso;
    reg [15:0] pack_current;
    reg [11:0] lmu0_temp_die, lmu1_temp_die, lmu2_temp_die;
    reg [15:0] lmu0_soc, lmu1_soc, lmu2_soc;
    reg [15:0] lmu0_soh, lmu1_soh, lmu2_soh;
    reg lmu0_fault, lmu1_fault, lmu2_fault;
    reg [7:0] lmu0_fault_code, lmu1_fault_code, lmu2_fault_code;
    wire spi_sclk, spi_mosi;
    wire [2:0] spi_cs_n;
    wire [15:0] pack_soc_avg, pack_soh_avg;
    wire global_fault;
    wire [7:0] global_fault_code;
    wire [1:0] active_lmu_id;
    wire poll_busy;
    wire current_warn, current_trip, thermal_warn, thermal_trip, lmu_count_fault;
    wire [15:0] allowed_current;
    wire [7:0] supervisor_code;
    wire [11:0] max_temp_seen;

    integer pass_count;
    integer fail_count;

    bms_master_control_unit_enhanced dut (
        .clk(clk), .rst_n(rst_n), .start_poll(start_poll), .spi_miso(spi_miso), .pack_current(pack_current),
        .lmu0_temp_die(lmu0_temp_die), .lmu1_temp_die(lmu1_temp_die), .lmu2_temp_die(lmu2_temp_die),
        .lmu0_soc(lmu0_soc), .lmu1_soc(lmu1_soc), .lmu2_soc(lmu2_soc), .lmu0_soh(lmu0_soh), .lmu1_soh(lmu1_soh), .lmu2_soh(lmu2_soh),
        .lmu0_fault(lmu0_fault), .lmu1_fault(lmu1_fault), .lmu2_fault(lmu2_fault),
        .lmu0_fault_code(lmu0_fault_code), .lmu1_fault_code(lmu1_fault_code), .lmu2_fault_code(lmu2_fault_code),
        .spi_sclk(spi_sclk), .spi_mosi(spi_mosi), .spi_cs_n(spi_cs_n), .pack_soc_avg(pack_soc_avg), .pack_soh_avg(pack_soh_avg),
        .global_fault(global_fault), .global_fault_code(global_fault_code), .active_lmu_id(active_lmu_id), .poll_busy(poll_busy),
        .current_warn(current_warn), .current_trip(current_trip), .thermal_warn(thermal_warn), .thermal_trip(thermal_trip),
        .lmu_count_fault(lmu_count_fault), .allowed_current(allowed_current), .supervisor_code(supervisor_code), .max_temp_seen(max_temp_seen)
    );

    initial begin clk = 0; forever #5 clk = ~clk; end

    task check;
        input cond;
        input [255:0] msg;
        begin
            if (cond) begin
                pass_count = pass_count + 1;
                $display("PASS: %0s", msg);
            end else begin
                fail_count = fail_count + 1;
                $display("FAIL: %0s", msg);
            end
        end
    endtask

    task poll_once;
        begin
            start_poll = 1'b1;
            @(posedge clk);
            start_poll = 1'b0;
            repeat(40) @(posedge clk);
        end
    endtask

    initial begin
        $dumpfile("sim/tb_bms_master_control_unit_enhanced.vcd");
        $dumpvars(0, tb_bms_master_control_unit_enhanced);

        pass_count = 0;
        fail_count = 0;
        rst_n = 0;
        start_poll = 0;
        spi_miso = 0;
        pack_current = 16'd120;
        lmu0_temp_die = 12'd35; lmu1_temp_die = 12'd40; lmu2_temp_die = 12'd38;
        lmu0_soc = 16'd810; lmu1_soc = 16'd780; lmu2_soc = 16'd750;
        lmu0_soh = 16'd970; lmu1_soh = 16'd940; lmu2_soh = 16'd910;
        lmu0_fault = 0; lmu1_fault = 0; lmu2_fault = 0;
        lmu0_fault_code = 8'h11; lmu1_fault_code = 8'h22; lmu2_fault_code = 8'h33;

        repeat(8) @(posedge clk);
        rst_n = 1;
        repeat(10) @(posedge clk);

        poll_once();
        $display("INFO MCU nominal: avg_soc=%0d avg_soh=%0d max_temp=%0d global_fault=%b code=0x%0h",
                 pack_soc_avg, pack_soh_avg, max_temp_seen, global_fault, global_fault_code);
        check(pack_soc_avg !== 16'hxxxx, "MCU average SOC is driven");
        check(pack_soh_avg !== 16'hxxxx, "MCU average SOH is driven");
        check(max_temp_seen !== 12'hxxx, "MCU max temperature is driven");

        pack_current = 16'd250;
        poll_once();
        check(current_warn !== 1'bx, "Current warning path is driven");

        pack_current = 16'd320;
        poll_once();
        check(current_trip !== 1'bx, "Current trip path is driven");

        pack_current = 16'd100;
        lmu2_temp_die = 12'd70;
        poll_once();
        check(thermal_warn !== 1'bx, "Thermal warning path is driven");

        lmu2_temp_die = 12'd90;
        poll_once();
        check(thermal_trip !== 1'bx, "Thermal trip path is driven");

        lmu2_temp_die = 12'd38;
        lmu0_soc = 16'd600; lmu1_soc = 16'd900; lmu2_soc = 16'd300;
        lmu0_soh = 16'd980; lmu1_soh = 16'd920; lmu2_soh = 16'd860;
        poll_once();
        check(pack_soc_avg !== 16'hxxxx, "MCU updates average SOC for new LMU values");
        check(pack_soh_avg !== 16'hxxxx, "MCU updates average SOH for new LMU values");

        lmu1_fault = 1'b1;
        poll_once();
        check(global_fault !== 1'bx, "Global fault output is driven when LMU fault present");
        check(global_fault_code !== 8'hxx, "Global fault code is driven when LMU fault present");

        lmu1_fault = 1'b0;
        lmu0_fault = 1'b1;
        poll_once();
        check(global_fault_code !== 8'hxx, "Fault code remains driven for LMU0 fault case");

        lmu0_fault = 1'b0;
        lmu2_fault = 1'b1;
        poll_once();
        check(global_fault_code !== 8'hxx, "Fault code remains driven for LMU2 fault case");

        lmu2_fault = 1'b0;
        poll_once();
        check(global_fault !== 1'bx, "Global fault output remains driven after fault clear");

        $display("MCU TB SUMMARY: PASS=%0d FAIL=%0d", pass_count, fail_count);
        if (fail_count == 0) $display("TB_RESULT: PASS"); else $display("TB_RESULT: FAIL");
        #50;
        $finish;
    end
endmodule

bms_complete/sim/tb_bms_master_control_unit_enhanced.vcd
$date
	Tue Jun  2 21:43:21 2026
$end
$version
	Icarus Verilog
$end
$timescale
	1ns
$end
$scope module tb_bms_master_control_unit_enhanced $end
$var wire 1 ! thermal_warn $end
$var wire 1 " thermal_trip $end
$var wire 8 # supervisor_code [7:0] $end
$var wire 1 $ spi_sclk $end
$var wire 1 % spi_mosi $end
$var wire 3 & spi_cs_n [2:0] $end
$var wire 1 ' poll_busy $end
$var wire 16 ( pack_soh_avg [15:0] $end
$var wire 16 ) pack_soc_avg [15:0] $end
$var wire 12 * max_temp_seen [11:0] $end
$var wire 1 + lmu_count_fault $end
$var wire 8 , global_fault_code [7:0] $end
$var wire 1 - global_fault $end
$var wire 1 . current_warn $end
$var wire 1 / current_trip $end
$var wire 16 0 allowed_current [15:0] $end
$var wire 2 1 active_lmu_id [1:0] $end
$var reg 1 2 clk $end
$var reg 1 3 lmu0_fault $end
$var reg 8 4 lmu0_fault_code [7:0] $end
$var reg 16 5 lmu0_soc [15:0] $end
$var reg 16 6 lmu0_soh [15:0] $end
$var reg 12 7 lmu0_temp_die [11:0] $end
$var reg 1 8 lmu1_fault $end
$var reg 8 9 lmu1_fault_code [7:0] $end
$var reg 16 : lmu1_soc [15:0] $end
$var reg 16 ; lmu1_soh [15:0] $end
$var reg 12 < lmu1_temp_die [11:0] $end
$var reg 1 = lmu2_fault $end
$var reg 8 > lmu2_fault_code [7:0] $end
$var reg 16 ? lmu2_soc [15:0] $end
$var reg 16 @ lmu2_soh [15:0] $end
$var reg 12 A lmu2_temp_die [11:0] $end
$var reg 16 B pack_current [15:0] $end
$var reg 1 C rst_n $end
$var reg 1 D spi_miso $end
$var reg 1 E start_poll $end
$var integer 32 F fail_count [31:0] $end
$var integer 32 G pass_count [31:0] $end
$scope module dut $end
$var wire 4 H active_lmu_count [3:0] $end
$var wire 1 2 clk $end
$var wire 1 3 lmu0_fault $end
$var wire 8 I lmu0_fault_code [7:0] $end
$var wire 16 J lmu0_soc [15:0] $end
$var wire 16 K lmu0_soh [15:0] $end
$var wire 12 L lmu0_temp_die [11:0] $end
$var wire 1 8 lmu1_fault $end
$var wire 8 M lmu1_fault_code [7:0] $end
$var wire 16 N lmu1_soc [15:0] $end
$var wire 16 O lmu1_soh [15:0] $end
$var wire 12 P lmu1_temp_die [11:0] $end
$var wire 1 = lmu2_fault $end
$var wire 8 Q lmu2_fault_code [7:0] $end
$var wire 16 R lmu2_soc [15:0] $end
$var wire 16 S lmu2_soh [15:0] $end
$var wire 12 T lmu2_temp_die [11:0] $end
$var wire 16 U pack_current [15:0] $end
$var wire 1 C rst_n $end
$var wire 1 D spi_miso $end
$var wire 1 E start_poll $end
$var wire 1 ! thermal_warn $end
$var wire 1 " thermal_trip $end
$var wire 8 V supervisor_code [7:0] $end
$var wire 1 $ spi_sclk $end
$var wire 8 W spi_rx_byte [7:0] $end
$var wire 1 % spi_mosi $end
$var wire 1 X spi_done $end
$var wire 3 Y spi_cs_n [2:0] $end
$var wire 1 Z spi_busy $end
$var wire 1 + lmu_count_fault $end
$var wire 1 . current_warn $end
$var wire 1 / current_trip $end
$var wire 16 [ allowed_current [15:0] $end
$var parameter 3 \ ST_EVAL $end
$var parameter 3 ] ST_IDLE $end
$var parameter 3 ^ ST_LMU0 $end
$var parameter 3 _ ST_LMU1 $end
$var parameter 3 ` ST_LMU2 $end
$var reg 2 a active_lmu_id [1:0] $end
$var reg 1 - global_fault $end
$var reg 8 b global_fault_code [7:0] $end
$var reg 12 c max_temp_seen [11:0] $end
$var reg 16 d pack_soc_avg [15:0] $end
$var reg 16 e pack_soh_avg [15:0] $end
$var reg 1 ' poll_busy $end
$var reg 2 f spi_slave_sel [1:0] $end
$var reg 1 g spi_start $end
$var reg 8 h spi_tx_byte [7:0] $end
$var reg 3 i state [2:0] $end
$scope module u_curr_sup $end
$var wire 4 j active_lmu_count [3:0] $end
$var wire 1 2 clk $end
$var wire 1 - global_fault_in $end
$var wire 12 k max_temp_seen [11:0] $end
$var wire 16 l pack_current [15:0] $end
$var wire 1 C rst_n $end
$var parameter 4 m MCU_MAX_LMU_COUNT $end
$var parameter 16 n MCU_MAX_PACK_CURRENT $end
$var parameter 12 o MCU_MAX_TEMP $end
$var parameter 16 p MCU_WARN_PACK_CURRENT $end
$var parameter 12 q MCU_WARN_TEMP $end
$var reg 16 r allowed_current [15:0] $end
$var reg 1 / current_trip $end
$var reg 1 . current_warn $end
$var reg 1 + lmu_count_fault $end
$var reg 8 s supervisor_code [7:0] $end
$var reg 1 " thermal_trip $end
$var reg 1 ! thermal_warn $end
$upscope $end
$scope module u_spi_master $end
$var wire 1 2 clk $end
$var wire 1 D miso $end
$var wire 1 C rst_n $end
$var wire 2 t slave_sel [1:0] $end
$var wire 1 g start $end
$var wire 8 u tx_byte [7:0] $end
$var parameter 8 v CLK_DIV $end
$var parameter 2 w CPHA $end
$var parameter 2 x CPOL $end
$var parameter 2 y ST_DONE $end
$var parameter 2 z ST_IDLE $end
$var parameter 2 { ST_SHIFT $end
$var reg 4 | bit_cnt [3:0] $end
$var reg 1 Z busy $end
$var reg 8 } clk_cnt [7:0] $end
$var reg 3 ~ cs_n [2:0] $end
$var reg 1 X done $end
$var reg 1 % mosi $end
$var reg 8 !" rx_byte [7:0] $end
$var reg 8 "" rx_shift [7:0] $end
$var reg 1 $ sclk $end
$var reg 2 #" state [1:0] $end
$var reg 8 $" tx_shift [7:0] $end
$upscope $end
$upscope $end
$scope task check $end
$var reg 1 %" cond $end
$var reg 256 &" msg [255:0] $end
$upscope $end
$scope task poll_once $end
$upscope $end
$upscope $end
$enddefinitions $end
$comment Show the parameter values. $end
$dumpall
b1 {
b0 z
b10 y
b0 x
b0 w
b1000 v
b1000001 q
b11110000 p
b1010000 o
b100101100 n
b11 m
b11 `
b10 _
b1 ^
b0 ]
b100 \
$end
#0
$dumpvars
bx &"
x%"
b0 $"
b0 #"
b0 ""
b0 !"
b111 ~
b0 }
b0 |
b0 u
b0 t
b0 s
b100101100 r
b1111000 l
b0 k
b11 j
b0 i
b0 h
0g
b0 f
b0 e
b0 d
b0 c
b0 b
b0 a
b100101100 [
0Z
b111 Y
0X
b0 W
b0 V
b1111000 U
b100110 T
b1110001110 S
b1011101110 R
b110011 Q
b101000 P
b1110101100 O
b1100001100 N
b100010 M
b100011 L
b1111001010 K
b1100101010 J
b10001 I
b11 H
b0 G
b0 F
0E
0D
0C
b1111000 B
b100110 A
b1110001110 @
b1011101110 ?
b110011 >
0=
b101000 <
b1110101100 ;
b1100001100 :
b100010 9
08
b100011 7
b1111001010 6
b1100101010 5
b10001 4
03
02
b0 1
b100101100 0
0/
0.
0-
b0 ,
0+
b0 *
b0 )
b0 (
0'
b111 &
0%
0$
b0 #
0"
0!
$end
#5
12
#10
02
#15
12
#20
02
#25
12
#30
02
#35
12
#40
02
#45
12
#50
02
#55
12
#60
02
#65
12
#70
02
#75
1C
12
#80
02
#85
12
#90
02
#95
12
#100
02
#105
12
#110
02
#115
12
#120
02
#125
12
#130
02
#135
12
#140
02
#145
12
#150
02
#155
12
#160
02
#165
12
#170
02
#175
b1 i
1g
b10110000 h
b10110000 u
1'
1E
12
#180
02
#185
0g
b1 #"
b110 &
b110 Y
b110 ~
1%
b10110000 $"
1Z
0E
12
#190
02
#195
b1 }
12
#200
02
#205
b10 }
12
#210
02
#215
b11 }
12
#220
02
#225
b100 }
12
#230
02
#235
b101 }
12
#240
02
#245
b110 }
12
#250
02
#255
b111 }
12
#260
02
#265
0%
b1100000 $"
b1 |
1$
b0 }
12
#270
02
#275
b1 }
12
#280
02
#285
b10 }
12
#290
02
#295
b11 }
12
#300
02
#305
b100 }
12
#310
02
#315
b101 }
12
#320
02
#325
b110 }
12
#330
02
#335
b111 }
12
#340
02
#345
0$
b0 }
12
#350
02
#355
b1 }
12
#360
02
#365
b10 }
12
#370
02
#375
b11 }
12
#380
02
#385
b100 }
12
#390
02
#395
b101 }
12
#400
02
#405
b110 }
12
#410
02
#415
b111 }
12
#420
02
#425
1%
b11000000 $"
b10 |
1$
b0 }
12
#430
02
#435
b1 }
12
#440
02
#445
b10 }
12
#450
02
#455
b11 }
12
#460
02
#465
b100 }
12
#470
02
#475
b101 }
12
#480
02
#485
b110 }
12
#490
02
#495
b111 }
12
#500
02
#505
0$
b0 }
12
#510
02
#515
b1 }
12
#520
02
#525
b10 }
12
#530
02
#535
b11 }
12
#540
02
#545
b100 }
12
#550
02
#555
b101 }
12
#560
02
#565
b110 }
12
#570
02
#575
b111 }
12
#580
02
#585
b10100001 #
b10100001 V
b10100001 s
1.
b10000000 $"
b11 |
1$
b0 }
1E
b11111010 B
b11111010 U
b11111010 l
b11 G
b100110101000011010101010010000001101101011000010111100000100000011101000110010101101101011100000110010101110010011000010111010001110101011100100110010100100000011010010111001100100000011001000111001001101001011101100110010101101110 &"
1%"
12
#590
02
#595
b1 }
0E
12
#600
02
#605
b10 }
12
#610
02
#615
b11 }
12
#620
02
#625
b100 }
12
#630
02
#635
b101 }
12
#640
02
#645
b110 }
12
#650
02
#655
b111 }
12
#660
02
#665
0$
b0 }
12
#670
02
#675
b1 }
12
#680
02
#685
b10 }
12
#690
02
#695
b11 }
12
#700
02
#705
b100 }
12
#710
02
#715
b101 }
12
#720
02
#725
b110 }
12
#730
02
#735
b111 }
12
#740
02
#745
0%
b0 $"
b100 |
1$
b0 }
12
#750
02
#755
b1 }
12
#760
02
#765
b10 }
12
#770
02
#775
b11 }
12
#780
02
#785
b100 }
12
#790
02
#795
b101 }
12
#800
02
#805
b110 }
12
#810
02
#815
b111 }
12
#820
02
#825
0$
b0 }
12
#830
02
#835
b1 }
12
#840
02
#845
b10 }
12
#850
02
#855
b11 }
12
#860
02
#865
b100 }
12
#870
02
#875
b101 }
12
#880
02
#885
b110 }
12
#890
02
#895
b111 }
12
#900
02
#905
b101 |
1$
b0 }
12
#910
02
#915
b1 }
12
#920
02
#925
b10 }
12
#930
02
#935
b11 }
12
#940
02
#945
b100 }
12
#950
02
#955
b101 }
12
#960
02
#965
b110 }
12
#970
02
#975
b111 }
12
#980
02
#985
0$
b0 }
12
#990
02
#995
b1 }
b11100011 #
b11100011 V
b11100011 s
1/
1E
b101000000 B
b101000000 U
b101000000 l
b100 G
b10000110111010101110010011100100110010101101110011101000010000001110111011000010111001001101110011010010110111001100111001000000111000001100001011101000110100000100000011010010111001100100000011001000111001001101001011101100110010101101110 &"
12
#1000
02
#1005
b10 }
0E
12
#1010
02
#1015
b11 }
12
#1020
02
#1025
b100 }
12
#1030
02
#1035
b101 }
12
#1040
02
#1045
b110 }
12
#1050
02
#1055
b111 }
12
#1060
02
#1065
b110 |
1$
b0 }
12
#1070
02
#1075
b1 }
12
#1080
02
#1085
b10 }
12
#1090
02
#1095
b11 }
12
#1100
02
#1105
b100 }
12
#1110
02
#1115
b101 }
12
#1120
02
#1125
b110 }
12
#1130
02
#1135
b111 }
12
#1140
02
#1145
0$
b0 }
12
#1150
02
#1155
b1 }
12
#1160
02
#1165
b10 }
12
#1170
02
#1175
b11 }
12
#1180
02
#1185
b100 }
12
#1190
02
#1195
b101 }
12
#1200
02
#1205
b110 }
12
#1210
02
#1215
b111 }
12
#1220
02
#1225
b111 |
1$
b0 }
12
#1230
02
#1235
b1 }
12
#1240
02
#1245
b10 }
12
#1250
02
#1255
b11 }
12
#1260
02
#1265
b100 }
12
#1270
02
#1275
b101 }
12
#1280
02
#1285
b110 }
12
#1290
02
#1295
b111 }
12
#1300
02
#1305
0$
b0 }
12
#1310
02
#1315
b1 }
12
#1320
02
#1325
b10 }
12
#1330
02
#1335
b11 }
12
#1340
02
#1345
b100 }
12
#1350
02
#1355
b101 }
12
#1360
02
#1365
b110 }
12
#1370
02
#1375
b111 }
12
#1380
02
#1385
b10 #"
1$
b0 }
12
#1390
02
#1395
b0 #"
1X
0Z
0$
b111 &
b111 Y
b111 ~
12
#1400
02
#1405
b10 i
1g
b10110001 h
b10110001 u
b1 f
b1 t
b1 1
b1 a
b0 #
b0 V
b0 s
0/
0.
0X
b0 |
1E
b1000110 A
b1000110 T
b1100100 B
b1100100 U
b1100100 l
b101 G
b10000110111010101110010011100100110010101101110011101000010000001110100011100100110100101110000001000000111000001100001011101000110100000100000011010010111001100100000011001000111001001101001011101100110010101101110 &"
12
#1410
02
#1415
b1 #"
b101 &
b101 Y
b101 ~
1%
b10110001 $"
1Z
0g
0E
12
#1420
02
#1425
b1 }
12
#1430
02
#1435
b10 }
12
#1440
02
#1445
b11 }
12
#1450
02
#1455
b100 }
12
#1460
02
#1465
b101 }
12
#1470
02
#1475
b110 }
12
#1480
02
#1485
b111 }
12
#1490
02
#1495
0%
b1100010 $"
b1 |
1$
b0 }
12
#1500
02
#1505
b1 }
12
#1510
02
#1515
b10 }
12
#1520
02
#1525
b11 }
12
#1530
02
#1535
b100 }
12
#1540
02
#1545
b101 }
12
#1550
02
#1555
b110 }
12
#1560
02
#1565
b111 }
12
#1570
02
#1575
0$
b0 }
12
#1580
02
#1585
b1 }
12
#1590
02
#1595
b10 }
12
#1600
02
#1605
b11 }
12
#1610
02
#1615
b100 }
12
#1620
02
#1625
b101 }
12
#1630
02
#1635
b110 }
12
#1640
02
#1645
b111 }
12
#1650
02
#1655
1%
b11000100 $"
b10 |
1$
b0 }
12
#1660
02
#1665
b1 }
12
#1670
02
#1675
b10 }
12
#1680
02
#1685
b11 }
12
#1690
02
#1695
b100 }
12
#1700
02
#1705
b101 }
12
#1710
02
#1715
b110 }
12
#1720
02
#1725
b111 }
12
#1730
02
#1735
0$
b0 }
12
#1740
02
#1745
b1 }
12
#1750
02
#1755
b10 }
12
#1760
02
#1765
b11 }
12
#1770
02
#1775
b100 }
12
#1780
02
#1785
b101 }
12
#1790
02
#1795
b110 }
12
#1800
02
#1805
b111 }
12
#1810
02
#1815
b10001000 $"
b11 |
1$
b0 }
1E
b1011010 A
b1011010 T
b110 G
b10101000110100001100101011100100110110101100001011011000010000001110111011000010111001001101110011010010110111001100111001000000111000001100001011101000110100000100000011010010111001100100000011001000111001001101001011101100110010101101110 &"
12
#1820
02
#1825
b1 }
0E
12
#1830
02
#1835
b10 }
12
#1840
02
#1845
b11 }
12
#1850
02
#1855
b100 }
12
#1860
02
#1865
b101 }
12
#1870
02
#1875
b110 }
12
#1880
02
#1885
b111 }
12
#1890
02
#1895
0$
b0 }
12
#1900
02
#1905
b1 }
12
#1910
02
#1915
b10 }
12
#1920
02
#1925
b11 }
12
#1930
02
#1935
b100 }
12
#1940
02
#1945
b101 }
12
#1950
02
#1955
b110 }
12
#1960
02
#1965
b111 }
12
#1970
02
